dpsutil/__init__.py
dpsutil/attrdict/__init__.py
dpsutil/attrdict/attrdict.py
dpsutil/attrdict/decorator.py
dpsutil/attrdict/defaultdict.py
dpsutil/common/__init__.py
dpsutil/common/helper.py
dpsutil/common/hw.py
dpsutil/compression/__init__.py
dpsutil/compression/compression.py
dpsutil/cv/__init__.py
dpsutil/cv/adjust.py
dpsutil/cv/blur_detection.py
dpsutil/cv/face_align.py
dpsutil/cv/transform.py
dpsutil/dataframe/__init__.py
dpsutil/dataframe/convert/__init__.py
dpsutil/dataframe/convert/convert.py
dpsutil/dataframe/frame/__init__.py
dpsutil/dataframe/frame/frame.py
dpsutil/environment/__init__.py
dpsutil/environment/environment.py
dpsutil/hash/__init__.py
dpsutil/hash/hash.py
dpsutil/kafka/__init__.py
dpsutil/kafka/configs.py
dpsutil/kafka/consume.py
dpsutil/kafka/error.py
dpsutil/kafka/producer.py
dpsutil/log/__init__.py
dpsutil/log/logger.py
dpsutil/matlab/__init__.py
dpsutil/matlab/cp2tform.py
dpsutil/media/__init__.py
dpsutil/media/constant.py
dpsutil/media/image.py
dpsutil/media/tool.py
dpsutil/media/video.py
dpsutil/multiprocess/__init__.py
dpsutil/multiprocess/threading.py
dpsutil/option/__init__.py
dpsutil/option/options.py
dpsutil/redis/__init__.py
dpsutil/redis/wrapper.py
dpsutil/sort/__init__.py
dpsutil/triangle/__init__.py
dpsutil/triangle/tool.py
dpsutil/triangle/triangle.py
dpsutil/vector/__init__.py
dpsutil/vector/distance.py
dpsutil/vector/pool.py
tests/__init__.py
tests/kafka.py
tests/pool_test.py
tests/test_attrdict.py
dpsailab_util-1.4.2.dist-info/LICENSE
dpsailab_util-1.4.2.dist-info/METADATA
dpsailab_util-1.4.2.dist-info/WHEEL
dpsailab_util-1.4.2.dist-info/top_level.txt
dpsailab_util-1.4.2.dist-info/RECORD
