Metadata-Version: 2.1
Name: dpsailab-util
Version: 1.4.2
Summary: This repository contain all util for DPS AI Computer Vision's member
Home-page: https://github.com/connortran216/dpsutil216.git
Author: ConnorTran
Author-email: canhtran210699@gmail.com
License: UNKNOWN
Platform: UNKNOWN
Requires-Python: >=3.6
Requires-Dist: numpy
Requires-Dist: redis
Requires-Dist: confluent-kafka (==1.5.0)
Requires-Dist: lz4
Requires-Dist: blosc
Requires-Dist: ffmpeg-python
Requires-Dist: natsort
Requires-Dist: attrdict
Requires-Dist: PyTurboJPEG
Requires-Dist: opencv-python
